ruyaml/__init__.py
ruyaml/anchor.py
ruyaml/comments.py
ruyaml/compat.py
ruyaml/composer.py
ruyaml/configobjwalker.py
ruyaml/constructor.py
ruyaml/cyaml.py
ruyaml/dumper.py
ruyaml/emitter.py
ruyaml/error.py
ruyaml/events.py
ruyaml/loader.py
ruyaml/main.py
ruyaml/nodes.py
ruyaml/parser.py
ruyaml/py.typed
ruyaml/reader.py
ruyaml/representer.py
ruyaml/resolver.py
ruyaml/scalarbool.py
ruyaml/scalarfloat.py
ruyaml/scalarint.py
ruyaml/scalarstring.py
ruyaml/scanner.py
ruyaml/serializer.py
ruyaml/timestamp.py
ruyaml/tokens.py
ruyaml/util.py
ruyaml-0.91.0.dist-info/LICENSE
ruyaml-0.91.0.dist-info/METADATA
ruyaml-0.91.0.dist-info/WHEEL
ruyaml-0.91.0.dist-info/top_level.txt
ruyaml-0.91.0.dist-info/zip-safe
ruyaml-0.91.0.dist-info/RECORD
