Metadata-Version: 2.1
Name: ruyaml
Version: 0.91.0
Summary: ruyaml is a fork of ruamel.yaml
Home-page: https://github.com/pycontribs/ruyaml
Author: ruyaml Contributors
Author-email: pycontribs@googlegroups.com
Maintainer: Sorin Sbarnea
Maintainer-email: sorin.sbarnea@gmail.com
License: MIT license
Project-URL: Bug Tracker, https://github.com/pycontribs/ruyaml/issues
Project-URL: Release Management, https://github.com/pycontribs/ruyaml/releases
Project-URL: Source Code, https://github.com/pycontribs/ruyaml
Keywords: selinux,virtualenv
Platform: UNKNOWN
Classifier: Development Status :: 5 - Production/Stable
Classifier: Environment :: Console
Classifier: Intended Audience :: Developers
Classifier: Intended Audience :: Information Technology
Classifier: Intended Audience :: System Administrators
Classifier: License :: OSI Approved :: MIT License
Classifier: Natural Language :: English
Classifier: Operating System :: OS Independent
Classifier: Programming Language :: Python :: 3.6
Classifier: Programming Language :: Python :: 3.7
Classifier: Programming Language :: Python :: 3.8
Classifier: Programming Language :: Python :: 3.9
Classifier: Programming Language :: Python :: 3.10
Classifier: Topic :: Utilities
Requires-Python: >=3.6
Provides-Extra: docs
License-File: LICENSE
